dsr_agent/__init__.py
dsr_agent/dsr_agent_pb2.py
dsr_agent/dsr_agent_pb2.pyi
dsr_agent/dsr_agent_pb2_grpc.py
dsr_agent/grpc_agent.py
dsr_agent/http_agent.py
dsr_agent/logger.py
dsr_agent/message_package.py
dsr_agent/protos/dsr_agent.proto
dsr_agent-0.0.5.dist-info/METADATA
dsr_agent-0.0.5.dist-info/WHEEL
dsr_agent-0.0.5.dist-info/licenses/LICENSE
dsr_agent-0.0.5.dist-info/RECORD
